[
  {
    "passage": "Sea Slime Dolphins Submit willingly",
    "filepath": "overworld-town/loc-sea/events.twee",
    "key": "4_5_3_7|",
    "original": "You swim to be in the middle of the <<beastsplural>>. They all watch as you<<if $exposed gte 2>> give them a quick strip tease and <</if>> show off your <<genitals>>. You wiggle provocatively.",
    "translation": "",
    "pos": 13
  },
  {
    "passage": "Sea Slime Dolphins Submit willingly",
    "filepath": "overworld-town/loc-sea/events.twee",
    "key": "7_5_3_7|",
    "original": "The lead <<beasttype>> swims up to you and mounts you.",
    "translation": "",
    "pos": 221
  },
  {
    "passage": "Sea Slime Dolphins Submit willingly",
    "filepath": "overworld-town/loc-sea/events.twee",
    "key": "12_5_3_7|",
    "original": "<<link [[Next|Sea Dolphins Sex]]>><<set $sexstart to 1>><<set $phase to 1>><</link>>",
    "translation": "",
    "pos": 304
  },
  {
    "passage": "Sea Slime Dolphins Obey",
    "filepath": "overworld-town/loc-sea/events.twee",
    "key": "17_5_3_7|",
    "original": "You swim to be in the middle of the <<beastsplural>>. They all watch as you<<if $exposed gte 2>> strip and<</if>> show off your <<genitals>>.",
    "translation": "",
    "pos": 13
  },
  {
    "passage": "Sea Slime Dolphins Obey",
    "filepath": "overworld-town/loc-sea/events.twee",
    "key": "20_5_3_7|",
    "original": "The lead <<beasttype>> swims up to you and mounts you.",
    "translation": "",
    "pos": 165
  },
  {
    "passage": "Sea Slime Dolphins Obey",
    "filepath": "overworld-town/loc-sea/events.twee",
    "key": "25_5_3_7|",
    "original": "<<link [[Next|Sea Dolphins]]>><<set $molestationstart to 1>><</link>>",
    "translation": "",
    "pos": 248
  },
  {
    "passage": "Sea Slime Dolphins Defy",
    "filepath": "overworld-town/loc-sea/events.twee",
    "key": "33_5_3_7|",
    "original": "You turn to swim away from the <<beastsplural>> and feel a jolt of pain as the slime punishes you for your defiance. However, <span class=\"red\">it doesn't stop you, knowing that it can punish you in other ways.</span>",
    "translation": "",
    "pos": 116
  },
  {
    "passage": "Sea Slime Dolphins Defy",
    "filepath": "overworld-town/loc-sea/events.twee",
    "key": "35_5_3_7|",
    "original": "You turn and swim away from the <<beastsplural>>. The slime tries to overpower your will, and you feel a jolt of pain as it punishes you for your defiance. However, <span class=\"teal\">it's still worn out from overpowering you earlier.</span> You feel it try, <span class=\"green\">but fail,</span> to force your steps in the opposite direction.",
    "translation": "",
    "pos": 346
  },
  {
    "passage": "Sea Slime Dolphins Defy",
    "filepath": "overworld-town/loc-sea/events.twee",
    "key": "48_5_3_7|",
    "original": "You turn and try to swim away from the <<beastsplural>>, <span class=\"red\">but the slime overpowers your will.</span> It forces you to turn<<if $exposted gte 2>>, strip,<</if>> and present your naked genitals to them. You wiggle provocatively.",
    "translation": "",
    "pos": 986
  },
  {
    "passage": "Sea Slime Dolphins Defy",
    "filepath": "overworld-town/loc-sea/events.twee",
    "key": "53_5_3_7|",
    "original": "One of them starts rubbing against you while the other two prevent you from moving away.",
    "translation": "",
    "pos": 1292
  },
  {
    "passage": "Sea Slime Dolphins Defy",
    "filepath": "overworld-town/loc-sea/events.twee",
    "key": "56_5_3_7|",
    "original": "<<link [[Next|Sea Dolphins]]>><<set $molestationstart to 1>><</link>>",
    "translation": "",
    "pos": 1393
  },
  {
    "passage": "Sea Slime Dolphins Defy",
    "filepath": "overworld-town/loc-sea/events.twee",
    "key": "59_5_3_7|",
    "original": "You turn and swim away from the <<beastsplural>>. The slime tries to overpower your will, <span class=\"green\">but you resist its influence.</span> The <<beastsplural>> don't give chase.",
    "translation": "",
    "pos": 1479
  },
  {
    "passage": "Sea Slime Dolphins Defy",
    "filepath": "overworld-town/loc-sea/events.twee",
    "key": "63_5_3_7|",
    "original": "The slime retaliates with a jolt of pain.",
    "translation": "",
    "pos": 1708
  },
  {
    "passage": "Sea Dolphins",
    "filepath": "overworld-town/loc-sea/events.twee",
    "key": "86_5_3_7|",
    "original": "<span class=\"pink\">The <<beastsplural>> push you out to sea.</span>",
    "translation": "",
    "pos": 337
  },
  {
    "passage": "Sea Dolphins",
    "filepath": "overworld-town/loc-sea/events.twee",
    "key": "100_5_3_7|",
    "original": "<span id=\"next\"><<link [[Next|Sea Dolphins Finish]]>><</link>></span><<nexttext>>",
    "translation": "",
    "pos": 569
  },
  {
    "passage": "Sea Dolphins",
    "filepath": "overworld-town/loc-sea/events.twee",
    "key": "102_5_3_7|",
    "original": "<span id=\"next\"><<link [[Next|Sea Dolphins]]>><</link>></span><<nexttext>>",
    "translation": "",
    "pos": 661
  },
  {
    "passage": "Sea Dolphins Finish",
    "filepath": "overworld-town/loc-sea/events.twee",
    "key": "111_5_3_7|",
    "original": "The <<beasttype>> recoils in pain and fear, but another is eager for a go.",
    "translation": "",
    "pos": 90
  },
  {
    "passage": "Sea Dolphins Finish",
    "filepath": "overworld-town/loc-sea/events.twee",
    "key": "114_5_3_7|",
    "original": "<<link [[Next|Sea Dolphins]]>><</link>>",
    "translation": "",
    "pos": 203
  },
  {
    "passage": "Sea Dolphins Finish",
    "filepath": "overworld-town/loc-sea/events.twee",
    "key": "117_5_3_7|",
    "original": "The <<beasttype>> recoils in pain and fear.",
    "translation": "",
    "pos": 262
  },
  {
    "passage": "Sea Dolphins Finish",
    "filepath": "overworld-town/loc-sea/events.twee",
    "key": "120_5_3_7|",
    "original": "<<link [[Next|Sea Dolphins Finish]]>><<set $finish to 1>><</link>>",
    "translation": "",
    "pos": 344
  },
  {
    "passage": "Sea Dolphins Finish",
    "filepath": "overworld-town/loc-sea/events.twee",
    "key": "125_5_3_7|",
    "original": "Satisfied, the <<beasttype>> moves and another takes its turn.",
    "translation": "",
    "pos": 523
  },
  {
    "passage": "Sea Dolphins Finish",
    "filepath": "overworld-town/loc-sea/events.twee",
    "key": "128_5_3_7|",
    "original": "<<link [[Next|Sea Dolphins]]>><</link>>",
    "translation": "",
    "pos": 624
  },
  {
    "passage": "Sea Dolphins Finish",
    "filepath": "overworld-town/loc-sea/events.twee",
    "key": "131_5_3_7|",
    "original": "Satisfied, the <<beasttype>> moves away from you.",
    "translation": "",
    "pos": 683
  },
  {
    "passage": "Sea Dolphins Finish",
    "filepath": "overworld-town/loc-sea/events.twee",
    "key": "134_5_3_7|",
    "original": "<<link [[Next|Sea Dolphins Finish]]>><<set $finish to 1>><</link>>",
    "translation": "",
    "pos": 771
  },
  {
    "passage": "Sea Dolphins Finish",
    "filepath": "overworld-town/loc-sea/events.twee",
    "key": "138_5_3_7|",
    "original": "The <<beasttype>> whimpers and flees into the darkness of the sea.",
    "translation": "",
    "pos": 926
  },
  {
    "passage": "Sea Dolphins Finish",
    "filepath": "overworld-town/loc-sea/events.twee",
    "key": "140_5_3_7|",
    "original": "The <<beasttype>> leaves you floating in the water.",
    "translation": "",
    "pos": 1052
  },
  {
    "passage": "Sea Dolphins Finish",
    "filepath": "overworld-town/loc-sea/events.twee",
    "key": "142_5_3_7|",
    "original": "Feeling that you're more trouble than you're worth, the <<beastsplural>> flee into the sea.",
    "translation": "",
    "pos": 1164
  },
  {
    "passage": "Sea Dolphins Finish",
    "filepath": "overworld-town/loc-sea/events.twee",
    "key": "144_5_3_7|",
    "original": "The <<beastsplural>> leave you spent and shivering in the water.",
    "translation": "",
    "pos": 1316
  },
  {
    "passage": "Sea Dolphins Finish",
    "filepath": "overworld-town/loc-sea/events.twee",
    "key": "146_5_3_7|",
    "original": "The <<beastsplural>> leave you spent and shivering in the water.",
    "translation": "",
    "pos": 1442
  },
  {
    "passage": "Sea Dolphins Finish",
    "filepath": "overworld-town/loc-sea/events.twee",
    "key": "149_5_3_7|",
    "original": "<<tearful>> you gather yourself.",
    "translation": "",
    "pos": 1527
  },
  {
    "passage": "Sea Dolphins Finish",
    "filepath": "overworld-town/loc-sea/events.twee",
    "key": "156_5_3_7|",
    "original": "A whistle blows, startling the <<beastsplural>>. A lifeguard in a small boat races toward you. The <<beastsplural>> make a chittering noise, then flee away from the shore. Seeing them leave, the lifeguard heads back to the beach.",
    "translation": "",
    "pos": 1689
  },
  {
    "passage": "Sea Dolphins Finish",
    "filepath": "overworld-town/loc-sea/events.twee",
    "key": "158_5_3_7|",
    "original": "<<tearful>> you gather yourself.",
    "translation": "",
    "pos": 1930
  },
  {
    "passage": "Sea Eels",
    "filepath": "overworld-town/loc-sea/events.twee",
    "key": "173_5_3_7|",
    "original": "<<swarminit \"eels\" \"swarm\" \"moving towards you\" \"encircle you\" \"fend off\" 1 9>>",
    "translation": "",
    "pos": 213
  },
  {
    "passage": "Sea Eels",
    "filepath": "overworld-town/loc-sea/events.twee",
    "key": "179_5_3_7|",
    "original": "You need to start swimming toward the buoy!",
    "translation": "",
    "pos": 381
  },
  {
    "passage": "Sea Eels",
    "filepath": "overworld-town/loc-sea/events.twee",
    "key": "181_5_3_7|",
    "original": "The buoy is still a long way off.",
    "translation": "",
    "pos": 458
  },
  {
    "passage": "Sea Eels",
    "filepath": "overworld-town/loc-sea/events.twee",
    "key": "183_5_3_7|",
    "original": "You've passed halfway to the buoy.",
    "translation": "",
    "pos": 524
  },
  {
    "passage": "Sea Eels",
    "filepath": "overworld-town/loc-sea/events.twee",
    "key": "185_5_3_7|",
    "original": "You're almost at the buoy.",
    "translation": "",
    "pos": 591
  },
  {
    "passage": "Sea Eels",
    "filepath": "overworld-town/loc-sea/events.twee",
    "key": "187_5_3_7|",
    "original": "The buoy is within arm's reach!",
    "translation": "",
    "pos": 628
  },
  {
    "passage": "Sea Eels",
    "filepath": "overworld-town/loc-sea/events.twee",
    "key": "194_5_3_7|",
    "original": "<span id=\"next\"><<link [[Next|Sea Eels Finish]]>><</link>></span><<nexttext>>",
    "translation": "",
    "pos": 775
  },
  {
    "passage": "Sea Eels",
    "filepath": "overworld-town/loc-sea/events.twee",
    "key": "196_5_3_7|",
    "original": "<span id=\"next\"><<link [[Next|Sea Eels]]>><</link>></span><<nexttext>>",
    "translation": "",
    "pos": 863
  },
  {
    "passage": "Sea Eels Finish",
    "filepath": "overworld-town/loc-sea/events.twee",
    "key": "203_5_3_7|",
    "original": "It's all just too much for you. You pass out.",
    "translation": "",
    "pos": 44
  },
  {
    "passage": "Sea Eels Finish",
    "filepath": "overworld-town/loc-sea/events.twee",
    "key": "218_5_3_7|",
    "original": "<<link [[Next|Passout Beach]]>><<pass 1 hour>><</link>>",
    "translation": "",
    "pos": 348
  },
  {
    "passage": "Sea Eels Finish",
    "filepath": "overworld-town/loc-sea/events.twee",
    "key": "220_5_3_7|",
    "original": "<<tearful>> you haul yourself out of the water. The eels wriggle off of you to escape the open air. You cling to the buoy and hang above the writhing mass. The swarms soon dissipate and return to the depths.",
    "translation": "",
    "pos": 414
  },
  {
    "passage": "Sea Beach Molestation",
    "filepath": "overworld-town/loc-sea/events.twee",
    "key": "240_5_3_7|",
    "original": "You try to pull away, but <<he>> won't let you!",
    "translation": "",
    "pos": 253
  },
  {
    "passage": "Sea Beach Molestation",
    "filepath": "overworld-town/loc-sea/events.twee",
    "key": "267_5_3_7|",
    "original": "<span id=\"next\"><<link [[Next|Sea Beach Molestation Finish]]>><</link>></span><<nexttext>>",
    "translation": "",
    "pos": 816
  },
  {
    "passage": "Sea Beach Molestation",
    "filepath": "overworld-town/loc-sea/events.twee",
    "key": "269_5_3_7|",
    "original": "<span id=\"next\"><<link [[Next|Sea Beach Molestation]]>><</link>></span><<nexttext>>",
    "translation": "",
    "pos": 917
  },
  {
    "passage": "Sea Beach Molestation Finish",
    "filepath": "overworld-town/loc-sea/events.twee",
    "key": "276_5_3_7|",
    "original": "The <<person>> looks around for someone else to hassle.",
    "translation": "",
    "pos": 43
  },
  {
    "passage": "Sea Beach Molestation Finish",
    "filepath": "overworld-town/loc-sea/events.twee",
    "key": "279_5_3_7|",
    "original": "<<He>> falls backwards into the water. By the time <<he>> recovers, you've disappeared into the crowds. <<tearful>> you gather yourself.",
    "translation": "",
    "pos": 143
  },
  {
    "passage": "Sea Beach Molestation Finish",
    "filepath": "overworld-town/loc-sea/events.twee",
    "key": "283_5_3_7|",
    "original": "Satisfied, <<he>> kicks you and swims away.",
    "translation": "",
    "pos": 394
  },
  {
    "passage": "Sea Beach Molestation Finish",
    "filepath": "overworld-town/loc-sea/events.twee",
    "key": "286_5_3_7|",
    "original": "Without a word, <<he>> leaves you floating in the water.",
    "translation": "",
    "pos": 487
  },
  {
    "passage": "Sea Beach Molestation Finish",
    "filepath": "overworld-town/loc-sea/events.twee",
    "key": "288_5_3_7|",
    "original": "Smiling, <<he>> kisses you on the cheek. <<He>> leaves you floating in the water.",
    "translation": "",
    "pos": 556
  },
  {
    "passage": "Sea Beach Molestation Finish",
    "filepath": "overworld-town/loc-sea/events.twee",
    "key": "291_5_3_7|",
    "original": "<<tearful>> you gather yourself.",
    "translation": "",
    "pos": 658
  },
  {
    "passage": "Sea Beach Molestation Finish",
    "filepath": "overworld-town/loc-sea/events.twee",
    "key": "294_5_3_7|",
    "original": "A whistle blows, startling the <<person>>. A lifeguard in a small boat races toward you. The <<person>> gives you an angry look, but leaves without further fuss. Seeing <<him>> leave, the lifeguard heads back to the beach. <<tearful>> you gather yourself.",
    "translation": "",
    "pos": 755
  },
  {
    "passage": "Boat Molestation",
    "filepath": "overworld-town/loc-sea/events.twee",
    "key": "318_5_3_7|",
    "original": "<span id=\"next\"><<link [[Next|Boat Molestation Finish]]>><</link>></span><<nexttext>>",
    "translation": "",
    "pos": 261
  },
  {
    "passage": "Boat Molestation",
    "filepath": "overworld-town/loc-sea/events.twee",
    "key": "320_5_3_7|",
    "original": "<span id=\"next\"><<link [[Next|Boat Molestation]]>><</link>></span><<nexttext>>",
    "translation": "",
    "pos": 357
  },
  {
    "passage": "Boat Molestation Finish",
    "filepath": "overworld-town/loc-sea/events.twee",
    "key": "328_5_3_7|",
    "original": "Finished with you, they dump you unceremoniously into the sea.",
    "translation": "",
    "pos": 73
  },
  {
    "passage": "Boat Molestation Finish",
    "filepath": "overworld-town/loc-sea/events.twee",
    "key": "332_5_3_7|",
    "original": "They recoil in pain. \"Fuck, it's a violent one,\" says the <<person1>><<person>>. They push you off the boat.",
    "translation": "",
    "pos": 195
  },
  {
    "passage": "Boat Molestation Finish",
    "filepath": "overworld-town/loc-sea/events.twee",
    "key": "336_5_3_7|",
    "original": "<<tearful>> you swim to the surface.",
    "translation": "",
    "pos": 340
  },
  {
    "passage": "Boat Molestation Finish",
    "filepath": "overworld-town/loc-sea/events.twee",
    "key": "340_5_3_7|",
    "original": "<<link [[Next|Sea]]>><<set $eventskip to 1>><</link>>",
    "translation": "",
    "pos": 414
  },
  {
    "passage": "Sea Vore",
    "filepath": "overworld-town/loc-sea/events.twee",
    "key": "356_5_3_7|",
    "original": "<span class=\"purple\">A $tentacles[0].fullDesc and $tentacles[1].fullDesc emerge from the creature and restrain your arms.</span>",
    "translation": "",
    "pos": 527
  },
  {
    "passage": "Sea Vore",
    "filepath": "overworld-town/loc-sea/events.twee",
    "key": "383_5_3_7|",
    "original": "<span id=\"next\"><<link [[Next|Sea Vore Finish]]>><</link>></span><<nexttext>>",
    "translation": "",
    "pos": 1299
  },
  {
    "passage": "Sea Vore",
    "filepath": "overworld-town/loc-sea/events.twee",
    "key": "385_5_3_7|",
    "original": "<span id=\"next\"><<link [[Next|Sea Vore]]>><</link>></span><<nexttext>>",
    "translation": "",
    "pos": 1387
  },
  {
    "passage": "Sea Vore Finish",
    "filepath": "overworld-town/loc-sea/events.twee",
    "key": "392_5_3_7|",
    "original": "It's all just too much for you. You pass out.",
    "translation": "",
    "pos": 66
  },
  {
    "passage": "Sea Vore Finish",
    "filepath": "overworld-town/loc-sea/events.twee",
    "key": "407_5_3_7|",
    "original": "<<link [[Next|Passout Beach]]>><<pass 1 hour>><</link>>",
    "translation": "",
    "pos": 370
  },
  {
    "passage": "Sea Vore Finish",
    "filepath": "overworld-town/loc-sea/events.twee",
    "key": "409_5_3_7|",
    "original": "<<tearful>> you haul yourself out of the $vorecreature's maw. It decides against pursuing you further, and disappears back into the depths.",
    "translation": "",
    "pos": 436
  },
  {
    "passage": "Sea Tangle Undress",
    "filepath": "overworld-town/loc-sea/events.twee",
    "key": "419_5_3_7|",
    "original": "You <<nervously>> remove your <<bottoms>>, exposing yourself beneath the water. Once removed, it's easy to untangle it from the seaweed.",
    "translation": "",
    "pos": 22
  },
  {
    "passage": "Sea Tangle",
    "filepath": "overworld-town/loc-sea/events.twee",
    "key": "426_5_3_7|",
    "original": "You start to untangle yourself without undressing. It takes a minute to free yourself.",
    "translation": "",
    "pos": 22
  },
  {
    "passage": "Sea Rape",
    "filepath": "overworld-town/loc-sea/events.twee",
    "key": "447_5_3_7|",
    "original": "<span id=\"next\"><<link [[Next|Sea Rape Finish]]>><</link>></span><<nexttext>>",
    "translation": "",
    "pos": 293
  },
  {
    "passage": "Sea Rape",
    "filepath": "overworld-town/loc-sea/events.twee",
    "key": "449_5_3_7|",
    "original": "<span id=\"next\"><<link [[Next|Sea Rape]]>><</link>></span><<nexttext>>",
    "translation": "",
    "pos": 381
  },
  {
    "passage": "Sea Rape Finish",
    "filepath": "overworld-town/loc-sea/events.twee",
    "key": "457_5_3_7|",
    "original": "<<He>> leaves you alone, and you struggle to the surface for air.",
    "translation": "",
    "pos": 73
  },
  {
    "passage": "Sea Rape Finish",
    "filepath": "overworld-town/loc-sea/events.twee",
    "key": "460_5_3_7|",
    "original": "<<tearful>> you cough and splutter.",
    "translation": "",
    "pos": 168
  },
  {
    "passage": "Sea Rape Finish",
    "filepath": "overworld-town/loc-sea/events.twee",
    "key": "466_5_3_7|",
    "original": "The <<person>> suddenly recoils from you. It looks like something is wrong with <<his>> diving mask. <<He>> swims away, and you struggle to the surface for air.",
    "translation": "",
    "pos": 300
  },
  {
    "passage": "Sea Rape Finish",
    "filepath": "overworld-town/loc-sea/events.twee",
    "key": "468_5_3_7|",
    "original": "<<tearful>> you cough and splutter.",
    "translation": "",
    "pos": 472
  },
  {
    "passage": "Sea Tentacles",
    "filepath": "overworld-town/loc-sea/events.twee",
    "key": "494_5_3_7|",
    "original": "<span id=\"next\"><<link [[Next|Sea Tentacles Finish]]>><</link>></span><<nexttext>>",
    "translation": "",
    "pos": 416
  },
  {
    "passage": "Sea Tentacles",
    "filepath": "overworld-town/loc-sea/events.twee",
    "key": "496_5_3_7|",
    "original": "<span id=\"next\"><<link [[Next|Sea Tentacles]]>><</link>></span><<nexttext>>",
    "translation": "",
    "pos": 509
  },
  {
    "passage": "Sea Tentacles Finish",
    "filepath": "overworld-town/loc-sea/events.twee",
    "key": "502_5_3_7|",
    "original": "The creature loses interest in you, and returns to the depths. <<tearful>> you struggle to stay afloat.",
    "translation": "",
    "pos": 22
  },
  {
    "passage": "Sea Dolphins Sex",
    "filepath": "overworld-town/loc-sea/events.twee",
    "key": "524_5_3_7|",
    "original": "You pet further and further down the $NPCList[0].type's belly. They take the hint, and swim closer to you in excitement.",
    "translation": "",
    "pos": 320
  },
  {
    "passage": "Sea Dolphins Sex",
    "filepath": "overworld-town/loc-sea/events.twee",
    "key": "539_5_3_7|",
    "original": "<span id=\"next\"><<link [[Next|Sea Dolphins Sex Finish]]>><</link>></span><<nexttext>>",
    "translation": "",
    "pos": 612
  },
  {
    "passage": "Sea Dolphins Sex",
    "filepath": "overworld-town/loc-sea/events.twee",
    "key": "541_5_3_7|",
    "original": "<span id=\"next\"><<link [[Next|Sea Dolphins Sex]]>><</link>></span><<nexttext>>",
    "translation": "",
    "pos": 708
  },
  {
    "passage": "Sea Dolphins Sex Finish",
    "filepath": "overworld-town/loc-sea/events.twee",
    "key": "551_5_3_7|",
    "original": "The $NPCList[_na].type recoils in pain and fear, but the next takes its turn.",
    "translation": "",
    "pos": 91
  },
  {
    "passage": "Sea Dolphins Sex Finish",
    "filepath": "overworld-town/loc-sea/events.twee",
    "key": "554_5_3_7|",
    "original": "<<link [[Next|Sea Dolphins Sex]]>><</link>>",
    "translation": "",
    "pos": 207
  },
  {
    "passage": "Sea Dolphins Sex Finish",
    "filepath": "overworld-town/loc-sea/events.twee",
    "key": "556_5_3_7|",
    "original": "The $NPCList[_na].type recoils in pain and fear.",
    "translation": "",
    "pos": 263
  },
  {
    "passage": "Sea Dolphins Sex Finish",
    "filepath": "overworld-town/loc-sea/events.twee",
    "key": "559_5_3_7|",
    "original": "<<link [[Next|Sea Dolphins Sex Finish]]>><<set $finish to 1>><</link>>",
    "translation": "",
    "pos": 350
  },
  {
    "passage": "Sea Dolphins Sex Finish",
    "filepath": "overworld-town/loc-sea/events.twee",
    "key": "564_5_3_7|",
    "original": "Satisfied, the $NPCList[_na].type moves and the next takes its turn.",
    "translation": "",
    "pos": 533
  },
  {
    "passage": "Sea Dolphins Sex Finish",
    "filepath": "overworld-town/loc-sea/events.twee",
    "key": "567_5_3_7|",
    "original": "<<link [[Next|Sea Dolphins Sex]]>><</link>>",
    "translation": "",
    "pos": 640
  },
  {
    "passage": "Sea Dolphins Sex Finish",
    "filepath": "overworld-town/loc-sea/events.twee",
    "key": "569_5_3_7|",
    "original": "Satisfied, the $NPCList[_na].type moves away from you.",
    "translation": "",
    "pos": 696
  },
  {
    "passage": "Sea Dolphins Sex Finish",
    "filepath": "overworld-town/loc-sea/events.twee",
    "key": "572_5_3_7|",
    "original": "<<link [[Next|Sea Dolphins Sex Finish]]>><<set $finish to 1>><</link>>",
    "translation": "",
    "pos": 789
  },
  {
    "passage": "Sea Dolphins Sex Finish",
    "filepath": "overworld-town/loc-sea/events.twee",
    "key": "576_5_3_7|",
    "original": "The <<beastsplural>> swim away from you.",
    "translation": "",
    "pos": 920
  },
  {
    "passage": "Sea Dolphins Sex Finish",
    "filepath": "overworld-town/loc-sea/events.twee",
    "key": "580_5_3_7|",
    "original": "The $NPCList[_na].type whimpers and flees into the darkness of the sea.",
    "translation": "",
    "pos": 1039
  },
  {
    "passage": "Sea Dolphins Sex Finish",
    "filepath": "overworld-town/loc-sea/events.twee",
    "key": "582_5_3_7|",
    "original": "The $NPCList[_na].type leaves you floating in the water.",
    "translation": "",
    "pos": 1172
  },
  {
    "passage": "Sea Dolphins Sex Finish",
    "filepath": "overworld-town/loc-sea/events.twee",
    "key": "584_5_3_7|",
    "original": "Feeling that you're more trouble than you're worth, the <<beastsplural>> flee into the sea.",
    "translation": "",
    "pos": 1291
  },
  {
    "passage": "Sea Dolphins Sex Finish",
    "filepath": "overworld-town/loc-sea/events.twee",
    "key": "586_5_3_7|",
    "original": "The <<beastsplural>> leave you spent and shivering in the water.",
    "translation": "",
    "pos": 1445
  },
  {
    "passage": "Sea Dolphins Sex Finish",
    "filepath": "overworld-town/loc-sea/events.twee",
    "key": "588_5_3_7|",
    "original": "The <<beastsplural>> leave you spent and shivering in the water.",
    "translation": "",
    "pos": 1573
  },
  {
    "passage": "Sea Dolphins Sex Finish",
    "filepath": "overworld-town/loc-sea/events.twee",
    "key": "592_5_3_7|",
    "original": "<<tearful>> you gather yourself.",
    "translation": "",
    "pos": 1669
  },
  {
    "passage": "Sea Dolphins Sex Finish",
    "filepath": "overworld-town/loc-sea/events.twee",
    "key": "599_5_3_7|",
    "original": "A whistle blows, startling the <<beastsplural>>. A lifeguard in a small boat races toward you. The <<beastsplural>> make a chittering noise, then flee away from the shore. Seeing them leave, the lifeguard heads back to the beach.",
    "translation": "",
    "pos": 1831
  },
  {
    "passage": "Sea Dolphins Sex Finish",
    "filepath": "overworld-town/loc-sea/events.twee",
    "key": "601_5_3_7|",
    "original": "<<tearful>> you gather yourself.",
    "translation": "",
    "pos": 2072
  },
  {
    "passage": "Sea Squid",
    "filepath": "overworld-town/loc-sea/events.twee",
    "key": "611_5_3_7|",
    "original": "You feel a thrill as you let the squid continue its devilish work.<<deviancy1>>",
    "translation": "",
    "pos": 47
  },
  {
    "passage": "Sea Pull",
    "filepath": "overworld-town/loc-sea/events.twee",
    "key": "618_5_3_7|",
    "original": "You pull the squid and its probing tentacles away from you.",
    "translation": "",
    "pos": 22
  },
  {
    "passage": "Sea Boat Call",
    "filepath": "overworld-town/loc-sea/events.twee",
    "key": "625_5_3_7|",
    "original": "You call out. After a moment, the boat steers in your direction. Someone throws a lifebuoy, which splashes down nearby. You grab hold of it, and are soon pulled on deck.",
    "translation": "",
    "pos": 63
  },
  {
    "passage": "Sea Boat Call",
    "filepath": "overworld-town/loc-sea/events.twee",
    "key": "628_5_3_7|",
    "original": "A <<person1>><<person>> helps pull you aboard. <<covered>> A <<person2>><<person>> and <<person3>><<person>> work elsewhere on the ship. <<if $exposed gte 1>>They pretend not to leer at you.<</if>>",
    "translation": "",
    "pos": 243
  },
  {
    "passage": "Sea Boat Call",
    "filepath": "overworld-town/loc-sea/events.twee",
    "key": "633_5_3_7|",
    "original": "<<person1>>\"You look like you need help,\" the <<person>> says, looking you up and down. \"No one rides for free, but it looks like you've got plenty to pay with.\" <<His>> ogling leaves no question as to the sort of payment <<he>> means.",
    "translation": "",
    "pos": 472
  },
  {
    "passage": "Sea Boat Call",
    "filepath": "overworld-town/loc-sea/events.twee",
    "key": "636_5_3_7|",
    "original": "<<link [[Accept|Sea Boat Accept]]>><</link>>",
    "translation": "",
    "pos": 720
  },
  {
    "passage": "Sea Boat Call",
    "filepath": "overworld-town/loc-sea/events.twee",
    "key": "638_5_3_7|",
    "original": "<<link [[Offer to dance for them instead|Sea Boat Dance]]>><</link>>",
    "translation": "",
    "pos": 772
  },
  {
    "passage": "Sea Boat Call",
    "filepath": "overworld-town/loc-sea/events.twee",
    "key": "640_5_3_7|",
    "original": "<<link [[Refuse|Sea Boat Refuse]]>><</link>>",
    "translation": "",
    "pos": 848
  },
  {
    "passage": "Sea Boat Call",
    "filepath": "overworld-town/loc-sea/events.twee",
    "key": "645_5_3_7|",
    "original": "<<person1>>\"Not what we were expecting to catch,\" the <<person>> laughs. \"Get yourself indoors, I'll get you something warm. We'll be back in port in a jiffy.\"",
    "translation": "",
    "pos": 942
  },
  {
    "passage": "Sea Boat Call",
    "filepath": "overworld-town/loc-sea/events.twee",
    "key": "648_5_3_7|",
    "original": "Your spend the journey sat in the ship's interior, a towel around your shoulders and a mug of tea warming your hands as the <<person>> regales you with tales of the high seas. The other crewmembers join in now and then, and scoff at some of <<his>> taller tales.",
    "translation": "",
    "pos": 1126
  },
  {
    "passage": "Sea Boat Call",
    "filepath": "overworld-town/loc-sea/events.twee",
    "key": "652_5_3_7|",
    "original": "You're soon back at the dock. They wave you goodbye as you climb ashore.",
    "translation": "",
    "pos": 1451
  },
  {
    "passage": "Sea Boat Call",
    "filepath": "overworld-town/loc-sea/events.twee",
    "key": "655_5_3_7|",
    "original": "<<link [[Next|Docks]]>><<endevent>><</link>>",
    "translation": "",
    "pos": 1536
  },
  {
    "passage": "Sea Boat Accept",
    "filepath": "overworld-town/loc-sea/events.twee",
    "key": "663_5_3_7|",
    "original": "You nod. The <<person1>><<person>> doesn't wait before shoving you to the deck.",
    "translation": "",
    "pos": 13
  },
  {
    "passage": "Sea Boat Accept",
    "filepath": "overworld-town/loc-sea/events.twee",
    "key": "666_5_3_7|",
    "original": "<<link [[Next|Sea Boat Rape]]>><<set $molestationstart to 1>><</link>>",
    "translation": "",
    "pos": 103
  },
  {
    "passage": "Sea Boat Rape",
    "filepath": "overworld-town/loc-sea/events.twee",
    "key": "689_5_3_7|",
    "original": "<span id=\"next\"><<link [[Next|Sea Boat Rape Finish]]>><</link>></span><<nexttext>>",
    "translation": "",
    "pos": 240
  },
  {
    "passage": "Sea Boat Rape",
    "filepath": "overworld-town/loc-sea/events.twee",
    "key": "691_5_3_7|",
    "original": "<span id=\"next\"><<link [[Next|Sea Boat Rape]]>><</link>></span><<nexttext>>",
    "translation": "",
    "pos": 333
  },
  {
    "passage": "Sea Boat Rape Finish",
    "filepath": "overworld-town/loc-sea/events.twee",
    "key": "700_5_3_7|",
    "original": "They let you stay indoors and give you some towels to dry with, at least. You soon pull into the dock.",
    "translation": "",
    "pos": 82
  },
  {
    "passage": "Sea Boat Rape Finish",
    "filepath": "overworld-town/loc-sea/events.twee",
    "key": "702_5_3_7|",
    "original": "<<tearful>> you climb from the ship.",
    "translation": "",
    "pos": 196
  },
  {
    "passage": "Sea Boat Rape Finish",
    "filepath": "overworld-town/loc-sea/events.twee",
    "key": "707_5_3_7|",
    "original": "<<link [[Next|Docks]]>><</link>>",
    "translation": "",
    "pos": 292
  },
  {
    "passage": "Sea Boat Rape Finish",
    "filepath": "overworld-town/loc-sea/events.twee",
    "key": "711_5_3_7|",
    "original": "You shove the <<person3>><<person>>, and <<he>> tumbles overboard. The <<person2>><<person>> rushes for another life buoy, while the <<person1>><<person>> reaches for a harpoon gun.",
    "translation": "",
    "pos": 342
  },
  {
    "passage": "Sea Boat Rape Finish",
    "filepath": "overworld-town/loc-sea/events.twee",
    "key": "714_5_3_7|",
    "original": "<<link [[Plead with them|Sea Boat Rape Plead]]>><</link>>",
    "translation": "",
    "pos": 536
  },
  {
    "passage": "Sea Boat Rape Finish",
    "filepath": "overworld-town/loc-sea/events.twee",
    "key": "716_5_3_7|",
    "original": "<<link [[Intimidate them|Sea Boat Rape Intimidate]]>><</link>>",
    "translation": "",
    "pos": 601
  },
  {
    "passage": "Sea Boat Rape Plead",
    "filepath": "overworld-town/loc-sea/events.twee",
    "key": "725_5_3_7|",
    "original": "\"P-please stop,\" you plead. \"I never wanted to fight.\"",
    "translation": "",
    "pos": 48
  },
  {
    "passage": "Sea Boat Rape Plead",
    "filepath": "overworld-town/loc-sea/events.twee",
    "key": "727_5_3_7|",
    "original": "\"Calm down,\" you say. \"No one has to know you got your asses kicked by a <<girl>> you met at sea.\"",
    "translation": "",
    "pos": 144
  },
  {
    "passage": "Sea Boat Rape Plead",
    "filepath": "overworld-town/loc-sea/events.twee",
    "key": "729_5_3_7|",
    "original": "\"I don't want to fight,\" you say. \"I just want to get back to shore.\"",
    "translation": "",
    "pos": 253
  },
  {
    "passage": "Sea Boat Rape Plead",
    "filepath": "overworld-town/loc-sea/events.twee",
    "key": "733_5_3_7|",
    "original": "<<dry>>The <<person1>><<person>> sneers at you, but winces and clutches <<his>> hips. \"Fine. But don't you dare breathe a word of this to anyone.\"",
    "translation": "",
    "pos": 341
  },
  {
    "passage": "Sea Boat Rape Plead",
    "filepath": "overworld-town/loc-sea/events.twee",
    "key": "736_5_3_7|",
    "original": "You spend the rest of the voyage indoors. You find towels to dry yourself with. You soon pull into the dock.",
    "translation": "",
    "pos": 498
  },
  {
    "passage": "Sea Boat Rape Plead",
    "filepath": "overworld-town/loc-sea/events.twee",
    "key": "739_5_3_7|",
    "original": "<<tearful>> you climb ashore.",
    "translation": "",
    "pos": 617
  },
  {
    "passage": "Sea Boat Rape Plead",
    "filepath": "overworld-town/loc-sea/events.twee",
    "key": "745_5_3_7|",
    "original": "<<link [[Next|Docks]]>><</link>>",
    "translation": "",
    "pos": 702
  },
  {
    "passage": "Sea Boat Rape Intimidate",
    "filepath": "overworld-town/loc-sea/events.twee",
    "key": "752_5_3_7|",
    "original": "\"I-I'm not afraid of you,\" you say, surprised by your confidence.",
    "translation": "",
    "pos": 48
  },
  {
    "passage": "Sea Boat Rape Intimidate",
    "filepath": "overworld-town/loc-sea/events.twee",
    "key": "754_5_3_7|",
    "original": "\"Your toys won't help,\" you say. \"Either get me back to shore, or I'm taking your ship and sailing there myself.\"",
    "translation": "",
    "pos": 155
  },
  {
    "passage": "Sea Boat Rape Intimidate",
    "filepath": "overworld-town/loc-sea/events.twee",
    "key": "756_5_3_7|",
    "original": "\"Give up while you still can,\" you say. \"I only want to get back to shore.\"",
    "translation": "",
    "pos": 279
  },
  {
    "passage": "Sea Boat Rape Intimidate",
    "filepath": "overworld-town/loc-sea/events.twee",
    "key": "761_5_3_7|",
    "original": "<<dry>>The <<person1>><<person>> sneers at you, but winces and clutches <<his>> hips. \"Fine. But don't you dare breathe a word of this to anyone.\"",
    "translation": "",
    "pos": 381
  },
  {
    "passage": "Sea Boat Rape Intimidate",
    "filepath": "overworld-town/loc-sea/events.twee",
    "key": "764_5_3_7|",
    "original": "You spend the rest of the voyage indoors. You find towels to dry yourself with, and soon pull into the dock.",
    "translation": "",
    "pos": 538
  },
  {
    "passage": "Sea Boat Rape Intimidate",
    "filepath": "overworld-town/loc-sea/events.twee",
    "key": "767_5_3_7|",
    "original": "<<tearful>> you climb ashore.",
    "translation": "",
    "pos": 657
  },
  {
    "passage": "Sea Boat Rape Intimidate",
    "filepath": "overworld-town/loc-sea/events.twee",
    "key": "774_5_3_7|",
    "original": "<<link [[Next|Docks]]>><</link>>",
    "translation": "",
    "pos": 754
  },
  {
    "passage": "Sea Boat Dance",
    "filepath": "overworld-town/loc-sea/events.twee",
    "key": "781_5_3_7|",
    "original": "\"W-wait,\" you say. \"I can dance for you. I can entertain you that way.\"",
    "translation": "",
    "pos": 48
  },
  {
    "passage": "Sea Boat Dance",
    "filepath": "overworld-town/loc-sea/events.twee",
    "key": "783_5_3_7|",
    "original": "\"Not letting scum like you touch me,\" you say. \"Sorry. You can look though. How about I give you a dance?\"",
    "translation": "",
    "pos": 161
  },
  {
    "passage": "Sea Boat Dance",
    "filepath": "overworld-town/loc-sea/events.twee",
    "key": "785_5_3_7|",
    "original": "\"I can dance for you instead,\" you say.",
    "translation": "",
    "pos": 278
  },
  {
    "passage": "Sea Boat Dance",
    "filepath": "overworld-town/loc-sea/events.twee",
    "key": "789_5_3_7|",
    "original": "The <<person1>><<person>> doesn't look impressed, but the <<person2>><<person>> chimes in. \"Come on captain. We'll be port soon, with whores a-plenty. How many of them can dance for shit though?\"",
    "translation": "",
    "pos": 336
  },
  {
    "passage": "Sea Boat Dance",
    "filepath": "overworld-town/loc-sea/events.twee",
    "key": "792_5_3_7|",
    "original": "The <<person1>><<person>> grumbles, but is convinced. They clear a space for you in the ship interior, open some drinks, and sit on a bench opposite. The <<person3>><<person>> turns on an old radio, and fiddles with the signal until <<he>> finds music.<<person1>>",
    "translation": "",
    "pos": 542
  },
  {
    "passage": "Sea Boat Dance",
    "filepath": "overworld-town/loc-sea/events.twee",
    "key": "796_5_3_7|",
    "original": "You're conscious of your <<nudity>>. It'll be difficult to dance without exposing yourself further. There's no way they'll give you towels before they're entertained.",
    "translation": "",
    "pos": 839
  },
  {
    "passage": "Sea Boat Dance",
    "filepath": "overworld-town/loc-sea/events.twee",
    "key": "799_5_3_7|",
    "original": "<<link [[Stay covered|Sea Boat Dance 2]]>><<set $phase to 2>><</link>><<dancedifficulty 1 1000>>",
    "translation": "",
    "pos": 1018
  },
  {
    "passage": "Sea Boat Dance",
    "filepath": "overworld-town/loc-sea/events.twee",
    "key": "801_5_3_7|",
    "original": "<<link [[Expose yourself to make dancing easier|Sea Boat Dance 2]]>><<set $phase to 1>><<fameexhibitionism 3>><<trauma 6>><<stress 6>><</link>><<dancedifficulty 1 600>><<gtrauma>><<gstress>>",
    "translation": "",
    "pos": 1122
  },
  {
    "passage": "Sea Boat Dance",
    "filepath": "overworld-town/loc-sea/events.twee",
    "key": "803_5_3_7|",
    "original": "You're conscious of your <<nudity>>. It'll be difficult to dance without exposing yourself further. There's no way they'll give you towels before they're entertained.",
    "translation": "",
    "pos": 1340
  },
  {
    "passage": "Sea Boat Dance",
    "filepath": "overworld-town/loc-sea/events.twee",
    "key": "806_5_3_7|",
    "original": "<<link [[Stay covered|Sea Boat Dance 2]]>><<set $phase to 2>><</link>><<dancedifficulty 1 1000>>",
    "translation": "",
    "pos": 1519
  },
  {
    "passage": "Sea Boat Dance",
    "filepath": "overworld-town/loc-sea/events.twee",
    "key": "808_5_3_7|",
    "original": "<<link [[Expose yourself to make dancing easier|Sea Boat Dance 2]]>><<set $phase to 1>><<fameexhibitionism 3>><<trauma 6>><<stress 6>><</link>><<dancedifficulty 1 600>><<gtrauma>><<gstress>>",
    "translation": "",
    "pos": 1623
  },
  {
    "passage": "Sea Boat Dance",
    "filepath": "overworld-town/loc-sea/events.twee",
    "key": "811_5_3_7|",
    "original": "<<link [[Dance|Sea Boat Dance 2]]>><<set $phase to 0>><</link>><<dancedifficulty 1 600>>",
    "translation": "",
    "pos": 1825
  },
  {
    "passage": "Sea Boat Dance 2",
    "filepath": "overworld-town/loc-sea/events.twee",
    "key": "817_5_3_7|",
    "original": "You dance for the three <<if $NPCList[0].pronoun is \"f\" and $NPCList[1].pronoun is \"f\" and $NPCList[2].pronoun is \"f\">>fisherwomen<<else>>fishermen<</if>>.",
    "translation": "",
    "pos": 13
  },
  {
    "passage": "Sea Boat Dance 2",
    "filepath": "overworld-town/loc-sea/events.twee",
    "key": "819_5_3_7|",
    "original": "You're confident in your abilities, and you think you know what they want to see.",
    "translation": "",
    "pos": 217
  },
  {
    "passage": "Sea Boat Dance 2",
    "filepath": "overworld-town/loc-sea/events.twee",
    "key": "821_5_3_7|",
    "original": "You think you're okay at this, but you hope their standards aren't too high.",
    "translation": "",
    "pos": 351
  },
  {
    "passage": "Sea Boat Dance 2",
    "filepath": "overworld-town/loc-sea/events.twee",
    "key": "823_5_3_7|",
    "original": "This isn't your first dance by any means, but it's a strange situation and you worry they won't like it.",
    "translation": "",
    "pos": 480
  },
  {
    "passage": "Sea Boat Dance 2",
    "filepath": "overworld-town/loc-sea/events.twee",
    "key": "825_5_3_7|",
    "original": "You don't really know what you're doing, but do your best to be graceful. You hope it's enough.",
    "translation": "",
    "pos": 595
  },
  {
    "passage": "Sea Boat Dance 2",
    "filepath": "overworld-town/loc-sea/events.twee",
    "key": "832_5_3_7|",
    "original": "They hoot as you expose your body for them, but you're not sure you could manage this and maintain dignity at the same time.",
    "translation": "",
    "pos": 807
  },
  {
    "passage": "Sea Boat Dance 2",
    "filepath": "overworld-town/loc-sea/events.twee",
    "key": "835_5_3_7|",
    "original": "Concealing your body at the same time proves difficult. You hope the coyness is worth something.",
    "translation": "",
    "pos": 975
  },
  {
    "passage": "Sea Boat Dance 2",
    "filepath": "overworld-town/loc-sea/events.twee",
    "key": "842_5_3_7|",
    "original": "<span class=\"green\">You hold their attention.</span> They reach to grope more than once, but you gracefully weave out of the way. They're cheering by the time the music stops, and demand an encore.",
    "translation": "",
    "pos": 1142
  },
  {
    "passage": "Sea Boat Dance 2",
    "filepath": "overworld-town/loc-sea/events.twee",
    "key": "847_5_3_7|",
    "original": "\"I-I danced for you,\" you say. \"Please bring me to shore.\"",
    "translation": "",
    "pos": 1401
  },
  {
    "passage": "Sea Boat Dance 2",
    "filepath": "overworld-town/loc-sea/events.twee",
    "key": "849_5_3_7|",
    "original": "\"That's my end of the agreement,\" you say. \"You better uphold yours.\"",
    "translation": "",
    "pos": 1503
  },
  {
    "passage": "Sea Boat Dance 2",
    "filepath": "overworld-town/loc-sea/events.twee",
    "key": "851_5_3_7|",
    "original": "\"I danced for you,\" you say. \"As we agreed.\"",
    "translation": "",
    "pos": 1585
  },
  {
    "passage": "Sea Boat Dance 2",
    "filepath": "overworld-town/loc-sea/events.twee",
    "key": "855_5_3_7|",
    "original": "\"Fine,\" the captain responds, finishing <<his>> drink.",
    "translation": "",
    "pos": 1651
  },
  {
    "passage": "Sea Boat Dance 2",
    "filepath": "overworld-town/loc-sea/events.twee",
    "key": "858_5_3_7|",
    "original": "They let you stay indoors and give you some towels to dry with. You soon pull into the dock.",
    "translation": "",
    "pos": 1718
  },
  {
    "passage": "Sea Boat Dance 2",
    "filepath": "overworld-town/loc-sea/events.twee",
    "key": "860_5_3_7|",
    "original": "<<tearful>> you climb from the ship.",
    "translation": "",
    "pos": 1822
  },
  {
    "passage": "Sea Boat Dance 2",
    "filepath": "overworld-town/loc-sea/events.twee",
    "key": "865_5_3_7|",
    "original": "<<link [[Next|Docks]]>><</link>>",
    "translation": "",
    "pos": 1928
  },
  {
    "passage": "Sea Boat Dance 2",
    "filepath": "overworld-town/loc-sea/events.twee",
    "key": "869_5_3_7|",
    "original": "Unfortunately you <span class=\"red\">slip</span> on the wet floor. \"Don't worry, <<girl>>,\" the <<person1>><<person>> says as <<his>> crew keels over laughing. \"We'll help you up.\"",
    "translation": "",
    "pos": 1978
  },
  {
    "passage": "Sea Boat Dance 2",
    "filepath": "overworld-town/loc-sea/events.twee",
    "key": "872_5_3_7|",
    "original": "<<link [[Next|Sea Boat Rape]]>><<set $molestationstart to 1>><</link>>",
    "translation": "",
    "pos": 2170
  },
  {
    "passage": "Sea Boat Refuse",
    "filepath": "overworld-town/loc-sea/events.twee",
    "key": "881_5_3_7|",
    "original": "\"You've got some nerve,\" the <<person1>><<person>> says. \"You're lucky I've a soft heart. Worse things could have found you, and I'm not talking about the fauna.\"",
    "translation": "",
    "pos": 34
  },
  {
    "passage": "Sea Boat Refuse",
    "filepath": "overworld-town/loc-sea/events.twee",
    "key": "884_5_3_7|",
    "original": "Despite <<his>> anger, <<he>> lets you stay indoors and even gives you towels to dry with. You soon pull into the dock.",
    "translation": "",
    "pos": 209
  },
  {
    "passage": "Sea Boat Refuse",
    "filepath": "overworld-town/loc-sea/events.twee",
    "key": "886_5_3_7|",
    "original": "<<tearful>> you climb from the ship.",
    "translation": "",
    "pos": 340
  },
  {
    "passage": "Sea Boat Refuse",
    "filepath": "overworld-town/loc-sea/events.twee",
    "key": "890_5_3_7|",
    "original": "<<link [[Next|Docks]]>><</link>>",
    "translation": "",
    "pos": 445
  },
  {
    "passage": "Sea Boat Refuse",
    "filepath": "overworld-town/loc-sea/events.twee",
    "key": "894_5_3_7|",
    "original": "The <<person1>><<person>> barks a laugh. \"You'd best play along, <<girl>>,\" <<he>> says as the <<person2>><<person>> and <<person3>><<person>> step closer.<<person1>> \"There are nastier devils than us out on the sea. And I'm not talking about the fauna.\"",
    "translation": "",
    "pos": 495
  },
  {
    "passage": "Sea Boat Refuse",
    "filepath": "overworld-town/loc-sea/events.twee",
    "key": "897_5_3_7|",
    "original": "<<link [[Next|Sea Boat Rape]]>><<set $molestationstart to 1>><</link>>",
    "translation": "",
    "pos": 762
  },
  {
    "passage": "Sea Boat Ignore",
    "filepath": "overworld-town/loc-sea/events.twee",
    "key": "905_5_3_7|",
    "original": "You avoid attracting attention to yourself.",
    "translation": "",
    "pos": 22
  },
  {
    "passage": "Sea Flotsam Reach",
    "filepath": "overworld-town/loc-sea/events.twee",
    "key": "913_5_3_7|",
    "original": "You reach into the seaweed,",
    "translation": "",
    "pos": 22
  },
  {
    "passage": "Sea Flotsam Reach",
    "filepath": "overworld-town/loc-sea/events.twee",
    "key": "916_5_3_7|",
    "original": "and wrap your fingers around something cold and hard. It's a compass. The glass is covered in grime, but beneath the point still turns north. Someone might be interested in this.",
    "translation": "",
    "pos": 264
  },
  {
    "passage": "Sea Flotsam Reach",
    "filepath": "overworld-town/loc-sea/events.twee",
    "key": "922_5_3_7|",
    "original": "but withdraw your fingers at a sharp, pinching pain. A crab hangs by one of its pincers.",
    "translation": "",
    "pos": 602
  },
  {
    "passage": "Sea Flotsam Ignore",
    "filepath": "overworld-town/loc-sea/events.twee",
    "key": "931_5_3_7|",
    "original": "You ignore the flotsam.",
    "translation": "",
    "pos": 22
  },
  {
    "passage": "Passout Sea",
    "filepath": "overworld-town/loc-sea/events.twee",
    "key": "937_5_3_7|",
    "original": "You've pushed yourself too much.",
    "translation": "",
    "pos": 0
  },
  {
    "passage": "Passout Sea",
    "filepath": "overworld-town/loc-sea/events.twee",
    "key": "943_5_3_7|",
    "original": "<<link [[Wake up|Pirate Intro]]>><</link>>",
    "translation": "",
    "pos": 148
  },
  {
    "passage": "Passout Sea",
    "filepath": "overworld-town/loc-sea/events.twee",
    "key": "946_5_3_7|",
    "original": "<<link [[Wake up|Beach Abduction]]>><<strip>><</link>>",
    "translation": "",
    "pos": 210
  },
  {
    "passage": "Sea Struggle",
    "filepath": "overworld-town/loc-sea/events.twee",
    "key": "977_5_3_7|",
    "original": "<span class=\"pink\">Another squid rises from the deep!</span>",
    "translation": "",
    "pos": 369
  },
  {
    "passage": "Sea Struggle",
    "filepath": "overworld-town/loc-sea/events.twee",
    "key": "985_5_3_7|",
    "original": "<span id=\"next\"><<link [[Next|Sea Struggle End]]>><</link>></span>",
    "translation": "",
    "pos": 508
  },
  {
    "passage": "Sea Struggle",
    "filepath": "overworld-town/loc-sea/events.twee",
    "key": "988_5_3_7|",
    "original": "<span id=\"next\"><<link [[Next|Sea Struggle]]>><</link>></span>",
    "translation": "",
    "pos": 591
  },
  {
    "passage": "Sea Struggle End",
    "filepath": "overworld-town/loc-sea/events.twee",
    "key": "996_5_3_7|",
    "original": "The squid return to the deep. <<tearful>> you tread water.",
    "translation": "",
    "pos": 13
  },
  {
    "passage": "Sea Struggle End",
    "filepath": "overworld-town/loc-sea/events.twee",
    "key": "1002_5_3_7|",
    "original": "<<link [[Next|Sea]]>><<set $eventskip to 1>><</link>>",
    "translation": "",
    "pos": 111
  },
  {
    "passage": "Sea Eye",
    "filepath": "overworld-town/loc-sea/events.twee",
    "key": "1008_5_3_7|",
    "original": "You look down, beneath your treading feet. You see nothing, at first. The surface of the water is too tempestuous, and the depths too gloomy. Then the water shifts just so, and you see it. At an impossible depth, a colossal eye staring up at you.",
    "translation": "",
    "pos": 13
  },
  {
    "passage": "Sea Eye",
    "filepath": "overworld-town/loc-sea/events.twee",
    "key": "1011_5_3_7|",
    "original": "A small wave washes over it, hiding it once more.",
    "translation": "",
    "pos": 270
  },
  {
    "passage": "Sea Eye",
    "filepath": "overworld-town/loc-sea/events.twee",
    "key": "1014_5_3_7|",
    "original": "<<link [[Next|Sea]]>><<set $eventskip to 1>><</link>>",
    "translation": "",
    "pos": 330
  },
  {
    "passage": "Sea Eye Refuse",
    "filepath": "overworld-town/loc-sea/events.twee",
    "key": "1020_5_3_7|",
    "original": "You resist the urge to look, until the feeling passes.",
    "translation": "",
    "pos": 13
  },
  {
    "passage": "Sea Eye Refuse",
    "filepath": "overworld-town/loc-sea/events.twee",
    "key": "1023_5_3_7|",
    "original": "<<link [[Next|Sea]]>><<set $eventskip to 1>><</link>>",
    "translation": "",
    "pos": 78
  },
  {
    "passage": "Sea Chest",
    "filepath": "overworld-town/loc-sea/events.twee",
    "key": "1029_5_3_7|",
    "original": "You swim toward the green rocks, your view of them disrupted by the waves.",
    "translation": "",
    "pos": 13
  },
  {
    "passage": "Sea Chest",
    "filepath": "overworld-town/loc-sea/events.twee",
    "key": "1031_5_3_7|",
    "original": "A sudden surge of water carries you the final stretch. <span class=\"green\">You use the momentum to land atop a rock with your feet.</span>",
    "translation": "",
    "pos": 113
  },
  {
    "passage": "Sea Chest",
    "filepath": "overworld-town/loc-sea/events.twee",
    "key": "1033_5_3_7|",
    "original": "A sudden surge of water carries you the final stretch, <span class=\"red\">slamming you atop a rock.</span><<ggpain>><<gstress>><<pain 8>><<stress 6>>",
    "translation": "",
    "pos": 262
  },
  {
    "passage": "Sea Chest",
    "filepath": "overworld-town/loc-sea/events.twee",
    "key": "1037_5_3_7|",
    "original": "You climb higher, using firm seaweed for purchase, careful not to slip. From up here you can see the entire island. It's not large, but in the middle are the remains of a circular wall. There's a shape in the centre, covered by seaweed.",
    "translation": "",
    "pos": 429
  },
  {
    "passage": "Sea Chest",
    "filepath": "overworld-town/loc-sea/events.twee",
    "key": "1040_5_3_7|",
    "original": "<<link [[Next|Sea Chest 2]]>><</link>>",
    "translation": "",
    "pos": 676
  },
  {
    "passage": "Sea Chest 2",
    "filepath": "overworld-town/loc-sea/events.twee",
    "key": "1048_5_3_7|",
    "original": "You climb down, and investigate. It's a chest. You peel back loose seaweed, revealing an engraving.",
    "translation": "",
    "pos": 34
  },
  {
    "passage": "Sea Chest 2",
    "filepath": "overworld-town/loc-sea/events.twee",
    "key": "1051_5_3_7|",
    "original": "\"Keep yer mitts off our booty,\" it says. Beneath it is a picture of a jawless skull with tentacles instead of teeth.",
    "translation": "",
    "pos": 144
  },
  {
    "passage": "Sea Chest 2",
    "filepath": "overworld-town/loc-sea/events.twee",
    "key": "1056_5_3_7|",
    "original": "It's locked, <span class=\"green\">but you think you could open it.</span>",
    "translation": "",
    "pos": 323
  },
  {
    "passage": "Sea Chest 2",
    "filepath": "overworld-town/loc-sea/events.twee",
    "key": "1058_5_3_7|",
    "original": "<<link [[Open|Sea Chest Open]]>><</link>>",
    "translation": "",
    "pos": 407
  },
  {
    "passage": "Sea Chest 2",
    "filepath": "overworld-town/loc-sea/events.twee",
    "key": "1061_5_3_7|",
    "original": "It's locked, <span class=\"red\">and beyond your ability to pick.</span>",
    "translation": "",
    "pos": 465
  },
  {
    "passage": "Sea Chest 2",
    "filepath": "overworld-town/loc-sea/events.twee",
    "key": "1065_5_3_7|",
    "original": "<<link [[Leave|Sea Chest Leave]]>><</link>>",
    "translation": "",
    "pos": 555
  },
  {
    "passage": "Sea Chest Leave",
    "filepath": "overworld-town/loc-sea/events.twee",
    "key": "1072_5_3_7|",
    "original": "You leave the chest where it lies, and return to the water.",
    "translation": "",
    "pos": 13
  },
  {
    "passage": "Sea Chest Leave",
    "filepath": "overworld-town/loc-sea/events.twee",
    "key": "1075_5_3_7|",
    "original": "<<link [[Next|Sea]]>><<set $eventskip to 1>><</link>>",
    "translation": "",
    "pos": 83
  },
  {
    "passage": "Sea Chest Open",
    "filepath": "overworld-town/loc-sea/events.twee",
    "key": "1082_5_3_7|",
    "original": "You open the lock, laying bare the treasure inside. A variety of stolen jewellery. It's still dry.",
    "translation": "",
    "pos": 13
  },
  {
    "passage": "Sea Chest Open",
    "filepath": "overworld-town/loc-sea/events.twee",
    "key": "1084_5_3_7|",
    "original": "Those look like actual diamonds. These could be worth a lot to a fence.",
    "translation": "",
    "pos": 133
  },
  {
    "passage": "Sea Chest Open",
    "filepath": "overworld-town/loc-sea/events.twee",
    "key": "1087_5_3_7|",
    "original": "They'd be worth a pretty penny to a fence.",
    "translation": "",
    "pos": 258
  },
  {
    "passage": "Sea Chest Open",
    "filepath": "overworld-town/loc-sea/events.twee",
    "key": "1090_5_3_7|",
    "original": "They might be worth something to a fence.",
    "translation": "",
    "pos": 339
  },
  {
    "passage": "Sea Chest Open",
    "filepath": "overworld-town/loc-sea/events.twee",
    "key": "1098_5_3_7|",
    "original": "There's also a ring, studded with blooms of coral. There's something vulgar about it. The metal looks like gold, but tarnished with age. This one belongs in a museum.",
    "translation": "",
    "pos": 717
  },
  {
    "passage": "Sea Chest Open",
    "filepath": "overworld-town/loc-sea/events.twee",
    "key": "1105_5_3_7|",
    "original": "<span class=\"blue\">There's nothing more you can learn from locks this simple.</span>",
    "translation": "",
    "pos": 965
  },
  {
    "passage": "Sea Chest Open",
    "filepath": "overworld-town/loc-sea/events.twee",
    "key": "1109_5_3_7|",
    "original": "A breeze from the sea whips through your hair. <span class=\"blue\">You shiver.</span>",
    "translation": "",
    "pos": 1087
  },
  {
    "passage": "Sea Chest Open",
    "filepath": "overworld-town/loc-sea/events.twee",
    "key": "1112_5_3_7|",
    "original": "You return to the water.",
    "translation": "",
    "pos": 1182
  },
  {
    "passage": "Sea Chest Open",
    "filepath": "overworld-town/loc-sea/events.twee",
    "key": "1115_5_3_7|",
    "original": "<<link [[Next|Sea]]>><<handheldon>><<set $eventskip to 1>><</link>>",
    "translation": "",
    "pos": 1217
  },
  {
    "passage": "Sea Pair Greet",
    "filepath": "overworld-town/loc-sea/events.twee",
    "key": "1121_5_3_7|",
    "original": "You wave at the pair as they draw closer.",
    "translation": "",
    "pos": 13
  },
  {
    "passage": "Sea Pair Greet",
    "filepath": "overworld-town/loc-sea/events.twee",
    "key": "1124_5_3_7|",
    "original": "\"We swam out here for some privacy,\" the <<person1>><<person>> says. \"But we don't mind a cutie like you joining us.\"",
    "translation": "",
    "pos": 65
  },
  {
    "passage": "Sea Pair Greet",
    "filepath": "overworld-town/loc-sea/events.twee",
    "key": "1127_5_3_7|",
    "original": "As <<he>> speaks, the <<person2>><<person>> swims around and behind you. <<Hes>> close enough to touch.",
    "translation": "",
    "pos": 193
  },
  {
    "passage": "Sea Pair Greet",
    "filepath": "overworld-town/loc-sea/events.twee",
    "key": "1130_5_3_7|",
    "original": "<<link [[Keep some distance|Sea Pair Distance]]>><<stress 6>><</link>><<difficulty 60>><<gstress>>",
    "translation": "",
    "pos": 307
  },
  {
    "passage": "Sea Pair Greet",
    "filepath": "overworld-town/loc-sea/events.twee",
    "key": "1132_5_3_7|",
    "original": "<<link [[Stay where you are|Sea Pair Stay]]>><</link>><<difficulty 40>>",
    "translation": "",
    "pos": 411
  },
  {
    "passage": "Sea Pair Distance",
    "filepath": "overworld-town/loc-sea/events.twee",
    "key": "1139_5_3_7|",
    "original": "You swim to the side, making it clear that you're wary of any funny business. <<person1>>\"We don't mean no harm,\" the <<person>> laughs while the <<person2>><<person>> swims back to <<person1>> <<him>>. <span class=\"green\">\"But we won't be pushy.\"</span> They turn and swim away.",
    "translation": "",
    "pos": 32
  },
  {
    "passage": "Sea Pair Distance",
    "filepath": "overworld-town/loc-sea/events.twee",
    "key": "1144_5_3_7|",
    "original": "You swim to the side, <span class=\"red\">but the <<person1>><<person>> cuts off your escape.</span> \"What's wrong?\" <<he>> laughs. \"Aren't we being friendly?\"",
    "translation": "",
    "pos": 371
  },
  {
    "passage": "Sea Pair Distance",
    "filepath": "overworld-town/loc-sea/events.twee",
    "key": "1146_5_3_7|",
    "original": "The <<person2>><<person>> swims up to you, and",
    "translation": "",
    "pos": 540
  },
  {
    "passage": "Sea Pair Distance",
    "filepath": "overworld-town/loc-sea/events.twee",
    "key": "1148_5_3_7|",
    "original": "grasps your <<breasts>>.",
    "translation": "",
    "pos": 615
  },
  {
    "passage": "Sea Pair Distance",
    "filepath": "overworld-town/loc-sea/events.twee",
    "key": "1150_5_3_7|",
    "original": "\"This slut's topless!\" <<he>> shouts in excitement, squeezing them.<<gtrauma>><<gstress>><<ggarousal>><<trauma 6>><<stress 6>><<arousal 1200>><<incgbreastinsecurity>>",
    "translation": "",
    "pos": 751
  },
  {
    "passage": "Sea Pair Distance",
    "filepath": "overworld-town/loc-sea/events.twee",
    "key": "1153_5_3_7|",
    "original": "\"Swimming out here exposed,\" the <<person1>><<person>> tuts. \"You must be a real pervert. I know just what you need.\"",
    "translation": "",
    "pos": 934
  },
  {
    "passage": "Sea Pair Distance",
    "filepath": "overworld-town/loc-sea/events.twee",
    "key": "1156_5_3_7|",
    "original": "<<link [[Next|Sea Pair Rape]]>><<set $molestationstart to 1>><</link>>",
    "translation": "",
    "pos": 1068
  },
  {
    "passage": "Sea Pair Distance",
    "filepath": "overworld-town/loc-sea/events.twee",
    "key": "1159_5_3_7|",
    "original": "<<He>> gropes and <<= _topless ? \"pinches your bare nipples\" : \"squeezes them beneath the fabric\">>.<<gtrauma>><<gstress>><<garousal>><<trauma 6>><<stress 6>><<arousal 600>><<incgbreastinsecurity>>",
    "translation": "",
    "pos": 1161
  },
  {
    "passage": "Sea Pair Distance",
    "filepath": "overworld-town/loc-sea/events.twee",
    "key": "1165_5_3_7|",
    "original": "grasps your <<genitals>>.",
    "translation": "",
    "pos": 1417
  },
  {
    "passage": "Sea Pair Distance",
    "filepath": "overworld-town/loc-sea/events.twee",
    "key": "1168_5_3_7|",
    "original": "\"This slut's wearing something odd,\" <<he>> says. \"It feels like <<print _material is \"parasite\" ? \"something soft\" : _material>>.\" <<He>> gives it a fruitless tug.",
    "translation": "",
    "pos": 1588
  },
  {
    "passage": "Sea Pair Distance",
    "filepath": "overworld-town/loc-sea/events.twee",
    "key": "1170_5_3_7|",
    "original": "\"I bet it's a chastity thing,\" the <<person1>><<person>> replies. \"So <<pshe>> must be a pervert. Let's give <<phim>> what <<pshe>> really wants.\"",
    "translation": "",
    "pos": 1768
  },
  {
    "passage": "Sea Pair Distance",
    "filepath": "overworld-town/loc-sea/events.twee",
    "key": "1173_5_3_7|",
    "original": "<<link [[Next|Sea Pair Rape]]>><<set $molestationstart to 1>><</link>>",
    "translation": "",
    "pos": 1931
  },
  {
    "passage": "Sea Pair Distance",
    "filepath": "overworld-town/loc-sea/events.twee",
    "key": "1176_5_3_7|",
    "original": "\"This slut's not wearing anything!\" <<he>> says. You recoil from <<his>> groping fingers, but <<he>> pulls you against <<his>> body with <<his>> other hand, immobilising you.",
    "translation": "",
    "pos": 2088
  },
  {
    "passage": "Sea Pair Distance",
    "filepath": "overworld-town/loc-sea/events.twee",
    "key": "1178_5_3_7|",
    "original": "\"Swimming out here exposed,\" the <<person1>><<person>> tuts. \"You must be a real pervert. I know just what you need.\"",
    "translation": "",
    "pos": 2278
  },
  {
    "passage": "Sea Pair Distance",
    "filepath": "overworld-town/loc-sea/events.twee",
    "key": "1181_5_3_7|",
    "original": "<<link [[Next|Sea Pair Rape]]>><<set $molestationstart to 1>><</link>>",
    "translation": "",
    "pos": 2412
  },
  {
    "passage": "Sea Pair Distance",
    "filepath": "overworld-town/loc-sea/events.twee",
    "key": "1184_5_3_7|",
    "original": "<<He>> gropes and squeezes it beneath the fabric.<<gtrauma>><<gstress>><<garousal>><<trauma 6>><<stress 6>><<arousal 600>><<incgbreastinsecurity>>",
    "translation": "",
    "pos": 2505
  },
  {
    "passage": "Sea Pair Practise",
    "filepath": "overworld-town/loc-sea/events.twee",
    "key": "1196_5_3_7|",
    "original": "\"I-I'm practising swimming,\" you say. \"I didn't mean to get in your way.\"",
    "translation": "",
    "pos": 48
  },
  {
    "passage": "Sea Pair Practise",
    "filepath": "overworld-town/loc-sea/events.twee",
    "key": "1198_5_3_7|",
    "original": "\"Don't worry about that,\" the <<person2>><<person>> laughs. \"We appreciated the visit.\"",
    "translation": "",
    "pos": 133
  },
  {
    "passage": "Sea Pair Practise",
    "filepath": "overworld-town/loc-sea/events.twee",
    "key": "1200_5_3_7|",
    "original": "\"I'm practising swimming,\" you say. \"I trust that's not a problem.\"",
    "translation": "",
    "pos": 262
  },
  {
    "passage": "Sea Pair Practise",
    "filepath": "overworld-town/loc-sea/events.twee",
    "key": "1202_5_3_7|",
    "original": "\"Not at all,\" the <<person2>><<person>> laughs. \"We'll leave you to it.\"",
    "translation": "",
    "pos": 341
  },
  {
    "passage": "Sea Pair Practise",
    "filepath": "overworld-town/loc-sea/events.twee",
    "key": "1204_5_3_7|",
    "original": "\"I'm practising swimming,\" you say. \"I don't mean to intrude.\"",
    "translation": "",
    "pos": 424
  },
  {
    "passage": "Sea Pair Practise",
    "filepath": "overworld-town/loc-sea/events.twee",
    "key": "1206_5_3_7|",
    "original": "\"No intrusion at all,\" the <<person2>><<person>> laughs. \"It's a free country.\"",
    "translation": "",
    "pos": 498
  },
  {
    "passage": "Sea Pair Practise",
    "filepath": "overworld-town/loc-sea/events.twee",
    "key": "1208_5_3_7|",
    "original": "<<He>> gives your <<bottom>> a swift spank before pulling away.<<gpain>><<garousal>><<pain 1>><<arousal 600>>",
    "translation": "",
    "pos": 586
  },
  {
    "passage": "Sea Pair Practise",
    "filepath": "overworld-town/loc-sea/events.twee",
    "key": "1211_5_3_7|",
    "original": "The pair disappear beyond the waves.",
    "translation": "",
    "pos": 706
  },
  {
    "passage": "Sea Pair Dragged",
    "filepath": "overworld-town/loc-sea/events.twee",
    "key": "1221_5_3_7|",
    "original": "\"I-I'm looking for people w-who-\" you say. \"Who need help getting back to shore.\"",
    "translation": "",
    "pos": 48
  },
  {
    "passage": "Sea Pair Dragged",
    "filepath": "overworld-town/loc-sea/events.twee",
    "key": "1223_5_3_7|",
    "original": "\"A good samaritan!\" the <<person2>><<person>> laughs. \"We won't interfere.\"",
    "translation": "",
    "pos": 141
  },
  {
    "passage": "Sea Pair Dragged",
    "filepath": "overworld-town/loc-sea/events.twee",
    "key": "1225_5_3_7|",
    "original": "\"I'm looking for people need saving,\" you say. \"You two alright?\"",
    "translation": "",
    "pos": 258
  },
  {
    "passage": "Sea Pair Dragged",
    "filepath": "overworld-town/loc-sea/events.twee",
    "key": "1227_5_3_7|",
    "original": "\"We're fine,\" the <<person2>><<person>> laughs. \"I hope your search is fruitless.\"",
    "translation": "",
    "pos": 335
  },
  {
    "passage": "Sea Pair Dragged",
    "filepath": "overworld-town/loc-sea/events.twee",
    "key": "1229_5_3_7|",
    "original": "\"I'm looking for anyone who needs help,\" you say. \"Dragged away by the riptide.\"",
    "translation": "",
    "pos": 428
  },
  {
    "passage": "Sea Pair Dragged",
    "filepath": "overworld-town/loc-sea/events.twee",
    "key": "1231_5_3_7|",
    "original": "\"Ain't seen any in need of saving,\" the <<person2>><<person>> says. \"But we won't stop you.\"",
    "translation": "",
    "pos": 520
  },
  {
    "passage": "Sea Pair Dragged",
    "filepath": "overworld-town/loc-sea/events.twee",
    "key": "1233_5_3_7|",
    "original": "<<He>> gives your <<bottom>> a swift spank before pulling away.<<gpain>><<garousal>><<pain 1>><<arousal 600>>",
    "translation": "",
    "pos": 621
  },
  {
    "passage": "Sea Pair Dragged",
    "filepath": "overworld-town/loc-sea/events.twee",
    "key": "1236_5_3_7|",
    "original": "The pair disappear behind the waves.",
    "translation": "",
    "pos": 741
  },
  {
    "passage": "Sea Pair Hunt",
    "filepath": "overworld-town/loc-sea/events.twee",
    "key": "1246_5_3_7|",
    "original": "\"I-I'm looking for bad people,\" you say. \"So I can teach them the error of their ways.\"",
    "translation": "",
    "pos": 48
  },
  {
    "passage": "Sea Pair Hunt",
    "filepath": "overworld-town/loc-sea/events.twee",
    "key": "1248_5_3_7|",
    "original": "\"Good luck on your search,\" the <<person2>><<person>> says. \"We'll let you know if we find any ourselves.\"",
    "translation": "",
    "pos": 147
  },
  {
    "passage": "Sea Pair Hunt",
    "filepath": "overworld-town/loc-sea/events.twee",
    "key": "1250_5_3_7|",
    "original": "\"I'm looking for rapists to fuck up,\" you say. \"Know any?\"",
    "translation": "",
    "pos": 295
  },
  {
    "passage": "Sea Pair Hunt",
    "filepath": "overworld-town/loc-sea/events.twee",
    "key": "1252_5_3_7|",
    "original": "\"Not a one,\" the <<person2>><<person>> laughs. \"But we know who to find if that changes.\"",
    "translation": "",
    "pos": 365
  },
  {
    "passage": "Sea Pair Hunt",
    "filepath": "overworld-town/loc-sea/events.twee",
    "key": "1254_5_3_7|",
    "original": "\"I'm keeping these waters safe,\" you say. \"Lots of riffraff about.\"",
    "translation": "",
    "pos": 465
  },
  {
    "passage": "Sea Pair Hunt",
    "filepath": "overworld-town/loc-sea/events.twee",
    "key": "1256_5_3_7|",
    "original": "\"We don't know any riffraff,\" the <<person2>><<person>> laughs. \"But we know who to find if we do.\"",
    "translation": "",
    "pos": 544
  },
  {
    "passage": "Sea Pair Hunt",
    "filepath": "overworld-town/loc-sea/events.twee",
    "key": "1258_5_3_7|",
    "original": "<<He>> gives your <<bottom>> a swift spank before pulling away.<<gpain>><<garousal>><<pain 1>><<arousal 600>>",
    "translation": "",
    "pos": 652
  },
  {
    "passage": "Sea Pair Stay",
    "filepath": "overworld-town/loc-sea/events.twee",
    "key": "1268_5_3_7|",
    "original": "You tread water, awaiting their approach. <span class=\"red\">The <<person2>><<person>> swims behind you,</span> and",
    "translation": "",
    "pos": 32
  },
  {
    "passage": "Sea Pair Stay",
    "filepath": "overworld-town/loc-sea/events.twee",
    "key": "1270_5_3_7|",
    "original": "grasps your <<breasts>>.",
    "translation": "",
    "pos": 175
  },
  {
    "passage": "Sea Pair Stay",
    "filepath": "overworld-town/loc-sea/events.twee",
    "key": "1273_5_3_7|",
    "original": "\"This slut's topless!\" <<he>> shouts in excitement, squeezing them.<<gtrauma>><<gstress>><<ggarousal>><<trauma 6>><<stress 6>><<arousal 1200>><<incgbreastinsecurity>>",
    "translation": "",
    "pos": 277
  },
  {
    "passage": "Sea Pair Stay",
    "filepath": "overworld-town/loc-sea/events.twee",
    "key": "1276_5_3_7|",
    "original": "\"Swimming out here exposed,\" the <<person1>><<person>> tuts. \"You must be a real pervert. I know just what you need.\"",
    "translation": "",
    "pos": 460
  },
  {
    "passage": "Sea Pair Stay",
    "filepath": "overworld-town/loc-sea/events.twee",
    "key": "1279_5_3_7|",
    "original": "<<link [[Next|Sea Pair Rape]]>><<set $molestationstart to 1>><</link>>",
    "translation": "",
    "pos": 594
  },
  {
    "passage": "Sea Pair Stay",
    "filepath": "overworld-town/loc-sea/events.twee",
    "key": "1282_5_3_7|",
    "original": "<<He>> gropes and <<= _topless ? \"pinches your bare nipples\" : \"squeezes them beneath the fabric\">>.<<gtrauma>><<gstress>><<garousal>><<trauma 6>><<stress 6>><<arousal 600>><<incgbreastinsecurity>>",
    "translation": "",
    "pos": 687
  },
  {
    "passage": "Sea Pair Stay",
    "filepath": "overworld-town/loc-sea/events.twee",
    "key": "1287_5_3_7|",
    "original": "grasps your <<genitals>>.",
    "translation": "",
    "pos": 942
  },
  {
    "passage": "Sea Pair Stay",
    "filepath": "overworld-town/loc-sea/events.twee",
    "key": "1290_5_3_7|",
    "original": "\"This slut's wearing something odd,\" <<he>> says. \"It feels like <<print _material is \"parasite\" ? \"something soft\" : _material>>.\" <<He>> gives it a fruitless tug.",
    "translation": "",
    "pos": 1113
  },
  {
    "passage": "Sea Pair Stay",
    "filepath": "overworld-town/loc-sea/events.twee",
    "key": "1292_5_3_7|",
    "original": "\"I bet it's a chastity thing,\" the <<person1>> the <<person>> replies. \"So <<pshe>> must be a pervert. Let's give <<phim>> what <<pshe>> really wants.\"",
    "translation": "",
    "pos": 1293
  },
  {
    "passage": "Sea Pair Stay",
    "filepath": "overworld-town/loc-sea/events.twee",
    "key": "1295_5_3_7|",
    "original": "<<link [[Next|Sea Pair Rape]]>><<set $molestationstart to 1>><</link>>",
    "translation": "",
    "pos": 1461
  },
  {
    "passage": "Sea Pair Stay",
    "filepath": "overworld-town/loc-sea/events.twee",
    "key": "1298_5_3_7|",
    "original": "\"This slut's not wearing anything!\" <<he>> says. You recoil from <<his>> groping fingers, but <<he>> pulls you against <<his>> body with <<his>> other hand, immobilising you.",
    "translation": "",
    "pos": 1618
  },
  {
    "passage": "Sea Pair Stay",
    "filepath": "overworld-town/loc-sea/events.twee",
    "key": "1300_5_3_7|",
    "original": "\"Swimming out here exposed,\" the <<person1>><<person>> tuts. \"You must be a real pervert. I know just what you need.\"",
    "translation": "",
    "pos": 1808
  },
  {
    "passage": "Sea Pair Stay",
    "filepath": "overworld-town/loc-sea/events.twee",
    "key": "1303_5_3_7|",
    "original": "<<link [[Next|Sea Pair Rape]]>><<set $molestationstart to 1>><</link>>",
    "translation": "",
    "pos": 1942
  },
  {
    "passage": "Sea Pair Stay",
    "filepath": "overworld-town/loc-sea/events.twee",
    "key": "1306_5_3_7|",
    "original": "<<He>> gropes and squeezes it beneath the fabric.<<gtrauma>><<gstress>><<garousal>><<trauma 6>><<stress 6>><<arousal 600>><<incgbreastinsecurity>>",
    "translation": "",
    "pos": 2035
  },
  {
    "passage": "Sea Pair Stay",
    "filepath": "overworld-town/loc-sea/events.twee",
    "key": "1313_5_3_7|",
    "original": "You tread water, awaiting their approach. <span class=\"green\">They stop some distance from you.</span>",
    "translation": "",
    "pos": 2247
  },
  {
    "passage": "Sea Pair Swim",
    "filepath": "overworld-town/loc-sea/events.twee",
    "key": "1324_5_3_7|",
    "original": "You turn and swim as fast as you can. You hear splashes behind you as the pair give chase, <span class=\"green\">but they're unable to keep up.</span> The sound of their paddling diminishes, until they disappear behind the waves.",
    "translation": "",
    "pos": 38
  },
  {
    "passage": "Sea Pair Swim",
    "filepath": "overworld-town/loc-sea/events.twee",
    "key": "1330_5_3_7|",
    "original": "You turn and swim as fast as you can. You hear splashes behind you as the pair give chase, gaining on you, <span class=\"red\">until a pair of hands clutches your ankle.</span>",
    "translation": "",
    "pos": 326
  },
  {
    "passage": "Sea Pair Swim",
    "filepath": "overworld-town/loc-sea/events.twee",
    "key": "1333_5_3_7|",
    "original": "\"What are you afraid of?\" the <<person1>><<person>> laughs as <<he>> pulls you closer. \"It's pretty private out here. Let's have some fun.\"",
    "translation": "",
    "pos": 513
  },
  {
    "passage": "Sea Pair Swim",
    "filepath": "overworld-town/loc-sea/events.twee",
    "key": "1336_5_3_7|",
    "original": "<<link [[Next|Sea Pair Rape]]>><<set $molestationstart to 1>><</link>>",
    "translation": "",
    "pos": 665
  },
  {
    "passage": "Sea Pair Rape",
    "filepath": "overworld-town/loc-sea/events.twee",
    "key": "1360_5_3_7|",
    "original": "<span id=\"next\"><<link [[Next|Sea Pair Rape Finish]]>><</link>></span><<nexttext>>",
    "translation": "",
    "pos": 253
  },
  {
    "passage": "Sea Pair Rape",
    "filepath": "overworld-town/loc-sea/events.twee",
    "key": "1362_5_3_7|",
    "original": "<span id=\"next\"><<link [[Next|Sea Pair Rape]]>><</link>></span><<nexttext>>",
    "translation": "",
    "pos": 346
  },
  {
    "passage": "Sea Pair Rape Finish",
    "filepath": "overworld-town/loc-sea/events.twee",
    "key": "1369_5_3_7|",
    "original": "\"See you around,\" the <<person1>><<person>> laughs. They swim away.",
    "translation": "",
    "pos": 72
  },
  {
    "passage": "Sea Pair Rape Finish",
    "filepath": "overworld-town/loc-sea/events.twee",
    "key": "1371_5_3_7|",
    "original": "<<tearful>> you tread water.",
    "translation": "",
    "pos": 151
  },
  {
    "passage": "Sea Pair Rape Finish",
    "filepath": "overworld-town/loc-sea/events.twee",
    "key": "1375_5_3_7|",
    "original": "The pair turn and swim away as fast as they can, throwing anxious glances over their shoulders.",
    "translation": "",
    "pos": 201
  },
  {
    "passage": "Sea Pair Rape Finish",
    "filepath": "overworld-town/loc-sea/events.twee",
    "key": "1377_5_3_7|",
    "original": "<<tearful>> you tread water.",
    "translation": "",
    "pos": 308
  }
]